<Room>
  <Saves />
  <index>0F</index>
  <area>04</area>
  <x>1F</x>
  <y>09</y>
  <width>03</width>
  <height>01</height>
  <upscroll>70</upscroll>
  <dnscroll>70</dnscroll>
  <specialGFX>00</specialGFX>
  <Doors>
    <Door>
      <toroom area="04" index="02" />
      <bitflag>00</bitflag>
      <direction>06</direction>
      <tilex>6</tilex>
      <tiley>4</tiley>
      <screenx>0A</screenx>
      <screeny>00</screeny>
      <distance>0300</distance>
      <doorcode>
        <ScrollData>
          <Change screen="10" scroll="00" />
          <Change screen="11" scroll="00" />
          <Change screen="12" scroll="00" />
          <Change screen="13" scroll="00" />
          <Change screen="14" scroll="00" />
          <Change screen="15" scroll="00" />
          <Change screen="16" scroll="00" />
        </ScrollData>
      </doorcode>
    </Door>
  </Doors>
  <States>
    <State condition="default">
      <LevelData Width="3" Height="1">
        <Layer1>
          <Screen X="0" Y="0">
        80AB 80AD 80AC 81E3 81E1 81E2 81E3 81E1 81E2 81E3 81E1 81E2 81E3 81E1 81E2 81E3
        80CC 80AA 80AA 81E1 81E2 81E3 81E1 81E2 81E3 81E1 81E2 81E3 81E1 81E2 81E3 81E1
        80AC 80AD 80AD 81E2 81E3 81E1 81E2 81E3 81E1 81E2 81E3 81E1 81E2 81E3 81E1 81E2
        80CC 80AB 80CC 00FF 00FF 00FF 00FF 00FF 00FF 00FF 81E1 81E2 81E3 81E1 81E2 81E3
        80AA 80AA 80CA 00FF 00FF 00FF 00FF 00FF 00FF 81E1 81E2 81E3 81E1 81E2 81E3 81E1
        80AB 80AD 80AC 00FF 00FF 00FF 00FF 00FF 00FF 00FF 00FF 81E1 81E2 81E3 81E1 81E2
        80CC 80AA 80AA 00FF 00FF 00FF 00FF 00FF 00FF 00FF 00FF 81E2 81E3 81E1 81E2 81E3
        80AC 80AD 80AD 84AA 80AA 00FF 00FF 00FF 00FF 00FF 00FF 00FF 81E1 81E2 81E3 81E1
        80AC 80CB 80AB 80CC 8CAA 80AA 00FF 00FF 00FF 00FF 00FF 81E1 81E2 81E3 81E1 81E2
        80CA 80AC 80AB 80CC 00FF 00FF 00FF 00FF 00FF 00FF 81E1 81E2 81E3 81E1 81E2 B1FE
        80CC 80AB 80CA 88CA 84AA 88AA 00FF 00FF 00FF 00FF 00FF 00FF 00FF 00FF 00FF B1FE
        84AD 80AD 80AD 84AD 84AD 80AD 84AD 80AD 81E1 81E2 81E3 81E1 81E2 81E3 81E1 81E2
        81E3 81E1 81E2 81E3 81E1 81E2 81E3 81E1 81E2 81E3 81E1 81E2 81E3 81E1 81E2 81E3
        81E2 81E3 81E1 81E2 81E3 81E1 81E2 81E3 81E1 81E2 81E3 81E1 81E2 81E3 81E1 81E2
        81E3 81E1 81E2 81E3 81E1 81E2 81E3 81E1 81E2 81E3 81E1 81E2 81E3 81E1 81E2 81E3
        81E2 81E3 81E1 81E2 81E3 81E1 81E2 81E3 81E1 81E2 81E3 81E1 81E2 81E3 81E1 81E2
      </Screen>
          <Screen X="1" Y="0">
        81E1 81E2 81E3 81E1 81E2 81E3 81E1 81E2 81E3 81E1 81E2 81E3 81E1 81E2 81E3 81E1
        81E2 81E3 81E1 81E2 81E3 81E1 81E2 81E3 81E1 81E2 81E3 81E1 81E2 81E3 81E1 81E2
        81E3 81E1 81E2 81E3 81E1 81E2 81E3 81E1 81E2 81E3 81E1 81E2 81E3 81E1 81E2 81E3
        81E1 81E2 81E3 81E1 81E2 81E3 81E1 81E2 81E3 81E1 81E2 81E3 81E1 81E2 81E3 00FF
        81E2 81E3 81E1 81E2 81E3 81E1 81E2 81E3 81E1 81E2 81E3 81E1 81E2 81E3 00FF 00FF
        81E3 81E1 81E2 81E3 81E1 81E2 81E3 81E1 81E2 81E3 81E1 81E2 81E3 00FF 00FF 00FF
        81E1 81E2 81E3 81E1 81E2 81E3 81E1 81E2 81E3 81E1 81E2 81E3 00FF 00FF 00FF 00FF
        81E2 81E3 81E1 81E2 81E3 81E1 81E2 81E3 81E1 81E2 81E3 00FF 00FF 00FF 00FF 00FF
        B1FE 81E1 81E2 81E3 81E1 81E2 81E3 81E1 81E2 81E3 00FF 00FF 00FF 00FF 00FF 00FF
        00FF 81E1 81E3 81E1 81E2 81E3 81E1 81E2 81E3 00FF 00FF 00FF 00FF 00FF 00FF 00FF
        00FF 00FF 00FF 00FF 00FF 00FF 00FF 00FF 00FF 00FF 00FF 00FF 00FF 00FF 00FF 00FF
        81E3 81E1 81E2 81E3 81E1 81E2 81E3 81E1 81E2 81E3 81E1 81E2 81E3 81E1 81E2 81E3
        81E1 81E2 81E3 81E1 81E2 81E3 81E1 81E2 81E3 81E1 81E2 81E3 81E1 81E2 81E3 81E1
        81E3 81E1 81E2 81E3 81E1 81E2 81E3 81E1 81E2 81E3 81E1 81E2 81E3 81E1 81E2 81E3
        81E1 81E2 81E3 81E1 81E2 81E3 81E1 81E2 81E3 81E1 81E2 81E3 81E1 81E2 81E3 81E1
        81E3 81E1 81E2 81E3 81E1 81E2 81E3 81E1 81E2 81E3 81E1 81E2 81E3 81E1 81E2 81E3
      </Screen>
          <Screen X="2" Y="0">
        81E2 81E3 81E1 81E2 81E3 81E1 81E2 81E3 81E1 81E2 81E3 81E1 81E2 81E3 81E1 81E2
        81E3 81E1 81E2 81E3 81E1 81E2 81E3 81E1 81E2 81E3 81E1 81E2 81E3 81E1 81E2 81E3
        A856 A856 A856 A856 A856 A856 A856 A856 A856 A856 A856 A856 A856 A856 81E1 81E2
        00FF 00FF 00FF 00FF 00FF 00FF 00FF 00FF 00FF 00FF 00FF 00FF 00FF 81E1 81E2 81E3
        00FF 00FF 00FF 00FF 00FF 00FF 00FF 00FF 00FF 00FF 00FF 00FF 00FF A856 81E1 81E2
        00FF 00FF 00FF 00FF 00FF 00FF 00FF 00FF 00FF 00FF 00FF 00FF 00FF 81E1 81E2 81E3
        00FF 00FF 00FF 00FF 00FF 00FF 00FF 00FF 00FF 00FF 00FF 00FF 00FF A856 81E1 81E2
        00FF 00FF 00FF 00FF 00FF 00FF 00FF 00FF 00FF 00FF 00FF 00FF 00FF 81E1 81E2 81E3
        00FF 00FF 00FF 00FF 00FF 00FF 00FF 00FF 00FF 00FF 00FF 00FF 00FF A856 81E1 81E2
        00FF 00FF 00FF 00FF 00FF 00FF 00FF 00FF 00FF 00FF 00FF 00FF 00FF 81E1 81E2 81E3
        00FF 00FF 00FF 00FF 00FF 00FF 00FF 00FF 00FF 00FF 00FF 00FF 00FF A856 81E1 81E2
        81E1 81E2 81E3 81E1 81E2 81E3 C41D 541C 501C 501D 81E1 81E2 81E3 81E1 81E2 81E3
        81E2 81E3 81E1 81E2 81E3 81E3 0443 0442 0042 0043 81E1 81E1 81E2 81E3 81E1 81E2
        81E1 81E2 81E3 81E1 81E2 81E3 9463 9462 9062 9063 81E1 81E2 81E3 81E1 81E2 81E3
        81E2 81E3 81E1 81E2 81E3 81E3 9463 9462 9062 9063 81E1 81E1 81E2 81E3 81E1 81E2
        81E1 81E2 81E3 81E1 81E2 81E3 9463 9462 9062 9063 81E1 81E2 81E3 81E1 81E2 81E3
      </Screen>
        </Layer1>
        <BTS>
          <Screen X="0" Y="0">
        00 00 00 00 00 00 00 00 00 00 00 00 00 00 00 00
        00 00 00 00 00 00 00 00 00 00 00 00 00 00 00 00
        00 00 00 00 00 00 00 00 00 00 00 00 00 00 00 00
        00 00 00 00 00 00 00 00 00 00 00 00 00 00 00 00
        00 00 00 00 00 00 00 00 00 00 00 00 00 00 00 00
        00 00 00 00 00 00 00 00 00 00 00 00 00 00 00 00
        00 00 00 00 00 00 00 00 00 00 00 00 00 00 00 00
        00 00 00 00 00 00 00 00 00 00 00 00 00 00 00 00
        00 00 00 00 00 00 00 00 00 00 00 00 00 00 00 00
        00 00 00 00 00 00 00 00 00 00 00 00 00 00 00 08
        00 00 00 00 00 00 00 00 00 00 00 00 00 00 00 08
        00 00 00 00 00 00 00 00 00 00 00 00 00 00 00 00
        00 00 00 00 00 00 00 00 00 00 00 00 00 00 00 00
        00 00 00 00 00 00 00 00 00 00 00 00 00 00 00 00
        00 00 00 00 00 00 00 00 00 00 00 00 00 00 00 00
        00 00 00 00 00 00 00 00 00 00 00 00 00 00 00 00
      </Screen>
          <Screen X="1" Y="0">
        00 00 00 00 00 00 00 00 00 00 00 00 00 00 00 00
        00 00 00 00 00 00 00 00 00 00 00 00 00 00 00 00
        00 00 00 00 00 00 00 00 00 00 00 00 00 00 00 00
        00 00 00 00 00 00 00 00 00 00 00 00 00 00 00 00
        00 00 00 00 00 00 00 00 00 00 00 00 00 00 00 00
        00 00 00 00 00 00 00 00 00 00 00 00 00 00 00 00
        00 00 00 00 00 00 00 00 00 00 00 00 00 00 00 00
        00 00 00 00 00 00 00 00 00 00 00 00 00 00 00 00
        0F 00 00 00 00 00 00 00 00 00 00 00 00 00 00 00
        00 00 00 00 00 00 00 00 00 00 00 00 00 00 00 00
        00 00 00 00 00 00 00 00 00 00 00 00 00 00 00 00
        00 00 00 00 00 00 00 00 00 00 00 00 00 00 00 00
        00 00 00 00 00 00 00 00 00 00 00 00 00 00 00 00
        00 00 00 00 00 00 00 00 00 00 00 00 00 00 00 00
        00 00 00 00 00 00 00 00 00 00 00 00 00 00 00 00
        00 00 00 00 00 00 00 00 00 00 00 00 00 00 00 00
      </Screen>
          <Screen X="2" Y="0">
        00 00 00 00 00 00 00 00 00 00 00 00 00 00 00 00
        00 00 00 00 00 00 00 00 00 00 00 00 00 00 00 00
        00 00 00 00 00 00 00 00 00 00 00 00 00 00 00 00
        00 00 00 00 00 00 00 00 00 00 00 00 00 00 00 00
        00 00 00 00 00 00 00 00 00 00 00 00 00 00 00 00
        00 00 00 00 00 00 00 00 00 00 00 00 00 00 00 00
        00 00 00 00 00 00 00 00 00 00 00 00 00 00 00 00
        00 00 00 00 00 00 00 00 00 00 00 00 00 00 00 00
        00 00 00 00 00 00 00 00 00 00 00 00 00 00 00 00
        00 00 00 00 00 00 00 00 00 00 00 00 00 00 00 00
        00 00 00 00 00 00 00 00 00 00 00 00 00 00 00 00
        00 00 00 00 00 00 42 FF FE FD 00 00 00 00 00 00
        00 00 00 00 00 00 00 00 00 00 00 00 00 00 00 00
        00 00 00 00 00 00 00 00 00 00 00 00 00 00 00 00
        00 00 00 00 00 00 00 00 00 00 00 00 00 00 00 00
        00 00 00 00 00 00 00 00 00 00 00 00 00 00 00 00
      </Screen>
        </BTS>
        <Layer2>
          <Screen X="0" Y="0">
        0096 0096 0096 0096 0096 0096 0096 0096 0096 0096 0096 0096 0096 0096 0096 0096
        0096 0096 0096 0096 0096 0096 0096 0096 0096 0096 0096 0096 0096 0096 0096 0096
        0096 0097 0096 0096 0096 0096 0096 0096 0096 0096 0096 0096 0096 0096 0096 0096
        0096 0097 02E0 02E1 02E2 06E2 06E1 06E0 02E0 02E1 0096 0096 0097 0096 0097 0096
        0096 0097 02E0 02E1 02E2 06E2 06E1 06E0 02E0 0096 0096 0097 0096 0097 0096 0096
        0096 0097 02E0 02E1 02E2 06E2 06E1 06E0 02E0 02E1 02E2 0096 0097 0096 0096 0096
        0096 0097 02E0 02E1 02E2 06E2 06E1 06E0 02E0 02E1 02E2 0096 0096 0097 0096 0096
        0096 0097 02E0 02E1 02E2 06E2 06E1 06E0 02E0 02E1 02E2 02E1 0096 0097 0096 0096
        0096 0097 02E0 02E1 02E2 06E2 06E1 06E0 02E0 02E1 02E2 0096 0097 0096 0097 0096
        0096 0097 02E0 02E1 02E2 06E2 06E1 06E0 02E0 02E1 0096 0097 0096 0097 0096 02E1
        0096 0097 02E0 02E1 02E2 06E2 06E1 06E0 02E0 02E1 02E2 06E2 06E1 06E0 02E0 02E1
        0293 0294 0295 0296 0293 0294 0295 0296 0382 0383 0382 0383 0383 0383 0383 0382
        0382 0383 0382 0383 0383 0383 0383 0382 0382 0382 0382 0382 0382 0382 0382 0382
        0382 0382 0382 0382 0382 0382 0382 0382 0382 0382 0382 0382 0382 0382 0382 0382
        0382 0382 0382 0382 0382 0382 0382 0382 0382 0382 0382 0382 0382 0383 0382 0383
        0382 0382 0382 0382 0382 0383 0382 0383 0382 0383 0382 0382 0382 0383 0382 0383
      </Screen>
          <Screen X="1" Y="0">
        0096 0096 0096 0096 0096 0096 0096 0096 0096 0096 0096 0096 0096 0096 0096 0096
        0096 0096 0096 0096 0096 0096 0096 0096 0096 0096 0096 0096 0096 0096 0096 0096
        0096 0097 0096 0097 0096 0097 0096 0097 0096 0097 0096 0097 0096 0097 0096 0097
        0097 0096 0097 0096 0097 0096 0097 0096 0097 0096 0097 0096 0097 0096 0097 06E0
        0096 0097 0096 0097 0096 0097 0096 0097 0096 0097 0096 0097 0096 0097 06E1 06E0
        0097 0096 0097 0096 0097 0096 0097 0096 0097 0096 0097 0096 0097 06E2 06E1 06E0
        0096 0097 0096 0097 0096 0097 0096 0097 0096 0097 0096 0097 02E2 06E2 06E1 06E0
        0097 0096 0097 0096 0097 0096 0097 0096 0097 0096 0097 02E1 02E2 06E2 06E1 06E0
        02E2 0096 0096 0097 0096 0097 0096 0097 0096 0097 02E0 02E1 02E2 06E2 06E1 06E0
        02E2 0096 0097 0096 0097 0096 0097 0096 0097 06E0 02E0 02E1 02E2 06E2 06E1 06E0
        02E2 06E2 06E1 06E0 02E0 02E1 02E2 06E2 06E1 06E0 02E0 02E1 02E2 06E2 06E1 06E0
        0383 0383 0383 0383 0382 0382 0383 0382 0383 0383 0383 0383 0382 0382 0383 0382
        0382 0382 0382 0382 0382 0382 0382 0382 0382 0382 0382 0382 0382 0382 0382 0382
        0382 0382 0382 0382 0382 0382 0382 0382 0382 0382 0382 0382 0382 0382 0382 0382
        0382 0382 0383 0382 0383 0382 0382 0382 0382 0382 0383 0382 0383 0382 0382 0382
        0382 0382 0383 0382 0383 0382 0383 0382 0382 0382 0383 0382 0383 0382 0383 0382
      </Screen>
          <Screen X="2" Y="0">
        0096 0096 0096 0096 0096 0096 0096 0096 0096 0096 0096 0096 0096 0096 0096 0096
        0096 0096 0096 0096 0096 0096 0096 0096 0096 0096 0096 0096 0096 0096 0096 0096
        02E0 02E1 02E2 06E2 06E1 06E0 02E0 02E1 02E2 06E2 06E1 06E0 02E0 06E0 0096 0096
        02E0 02E1 02E2 06E2 06E1 06E0 02E0 02E1 02E2 06E2 06E1 06E0 02E0 0096 0096 0096
        02E0 02E1 02E2 06E2 06E1 06E0 02E0 02E1 02E2 06E2 06E1 06E0 02E0 06E0 0096 0096
        02E0 02E1 02E2 06E2 06E1 06E0 02E0 02E1 02E2 06E2 06E1 06E0 02E0 0096 0096 0096
        02E0 02E1 02E2 06E2 06E1 06E0 02E0 02E1 02E2 06E2 06E1 06E0 02E0 06E0 0096 0096
        02E0 02E1 02E2 06E2 06E1 06E0 02E0 02E1 02E2 06E2 06E1 06E0 02E0 0096 0096 0096
        02E0 02E1 02E2 06E2 06E1 06E0 02E0 02E1 02E2 06E2 06E1 06E0 02E0 06E0 0096 0096
        02E0 02E1 02E2 06E2 06E1 06E0 02E0 02E1 02E2 06E2 06E1 06E0 02E0 0096 0096 0096
        02E0 02E1 02E2 06E2 06E1 06E0 02E0 02E1 02E2 06E2 06E1 06E0 02E0 06E0 0096 0096
        0383 0383 0383 0383 0382 0383 02E0 02E1 02E2 06E2 0382 0383 0382 0383 0383 0383
        0382 0382 0382 0382 0382 0383 02E0 02E1 02E2 06E2 0382 0382 0382 0382 0382 0382
        0382 0382 0382 0382 0382 0383 02E0 02E1 02E2 06E2 0382 0382 0382 0382 0382 0382
        0382 0382 0383 0382 0383 0383 02E0 02E1 02E2 06E2 0382 0382 0382 0382 0382 0383
        0382 0382 0383 0382 0383 0383 02E0 02E1 02E2 06E2 0382 0383 0382 0382 0382 0383
      </Screen>
        </Layer2>
      </LevelData>
      <GFXset>0B</GFXset>
      <music>0000</music>
      <FX1s>
        <FX1 default="true">
          <surfacestart>03C8</surfacestart>
          <surfacenew>FFFF</surfacenew>
          <surfacespeed>0000</surfacespeed>
          <surfacedelay>00</surfacedelay>
          <type>0C</type>
          <transparency1_A>16</transparency1_A>
          <transparency2_B>2E</transparency2_B>
          <liquidflags_C>07</liquidflags_C>
          <paletteflags>0F</paletteflags>
          <animationflags>FF</animationflags>
          <paletteblend>62</paletteblend>
        </FX1>
      </FX1s>
      <Enemies killcount="00" />
      <EnemyTypes />
      <layer2_type>Layer2</layer2_type>
      <layer2_xscroll>00</layer2_xscroll>
      <layer2_yscroll>00</layer2_yscroll>
      <ScrollData const="0000" />
      <roomvar>0000</roomvar>
      <FX2>0000</FX2>
      <PLMs>
        <PLM>
          <type>EF27</type>
          <x>05</x>
          <y>09</y>
          <arg>003B</arg>
        </PLM>
      </PLMs>
      <BGData />
      <layer1_2>91D3</layer1_2>
    </State>
  </States>
</Room>